trio_vis/__init__.py
trio_vis/config.py
trio_vis/desc_tree.py
trio_vis/protocol.py
trio_vis/registry.py
trio_vis/sc_logger.py
trio_vis/sc_monitor.py
trio_vis/trio_fake.py
trio_vis-0.1.0.dist-info/LICENSE
trio_vis-0.1.0.dist-info/WHEEL
trio_vis-0.1.0.dist-info/METADATA
trio_vis-0.1.0.dist-info/RECORD
