Metadata-Version: 2.1
Name: trio-vis
Version: 0.1.0
Summary: Structured Concurrency visualizer for trio
Home-page: https://github.com/ianchen-tw/trio-vis
License: MIT
Author: Ian Chen
Author-email: ianre657@gmail.com
Requires-Python: >=3.6.2,<4.0
Classifier: Development Status :: 2 - Pre-Alpha
Classifier: Environment :: Plugins
Classifier: Framework :: Trio
Classifier: Intended Audience :: Developers
Classifier: License :: OSI Approved :: MIT License
Classifier: Operating System :: OS Independent
Classifier: Programming Language :: Python :: 3
Classifier: Programming Language :: Python :: 3 :: Only
Classifier: Programming Language :: Python :: 3.10
Classifier: Programming Language :: Python :: 3.6
Classifier: Programming Language :: Python :: 3.7
Classifier: Programming Language :: Python :: 3.8
Classifier: Programming Language :: Python :: 3.9
Classifier: Topic :: Scientific/Engineering :: Visualization
Requires-Dist: attrs (>=21.2.0,<22.0.0)
Requires-Dist: pydantic (>=1.8.2,<2.0.0)
Requires-Dist: rich (>=9.13.0,<10.0.0)
Requires-Dist: trio (>=0.19.0,<0.20.0)
Requires-Dist: trio-typing (>=0.5.0,<0.6.0)
Requires-Dist: typing-extensions (>=3,<4)
Project-URL: Repository, https://github.com/ianchen-tw/trio-vis
